{
 "actions": [],
 "allow_rename": 1,
 "creation": "2025-08-25 15:34:40.102269",
 "doctype": "DocType",
 "editable_grid": 1,
 "engine": "InnoDB",
 "field_order": [
  "company",
  "column_break_cplj",
  "from_date",
  "to_date"
 ],
 "fields": [
  {
   "fieldname": "company",
   "fieldtype": "Link",
   "in_list_view": 1,
   "label": "Company",
   "options": "Company"
  },
  {
   "fieldname": "column_break_cplj",
   "fieldtype": "Column Break"
  },
  {
   "fieldname": "from_date",
   "fieldtype": "Date",
   "in_list_view": 1,
   "label": "From Date"
  },
  {
   "fieldname": "to_date",
   "fieldtype": "Date",
   "in_list_view": 1,
   "label": "To Date"
  }
 ],
 "grid_page_length": 50,
 "index_web_pages_for_search": 1,
 "istable": 1,
 "links": [],
 "modified": "2025-08-25 15:53:31.333930",
 "modified_by": "Administrator",
 "module": "Academic Management",
 "name": "Colleges",
 "owner": "Administrator",
 "permissions": [],
 "row_format": "Dynamic",
 "sort_field": "modified",
 "sort_order": "DESC",
 "states": []
}